{
  "generated_at": "2026-07-18T12:35:53.540Z",
  "folders": {
    "files": [
      ".gitignore",
      "app_tree.txt",
      "folders_tree.txt",
      "index.html",
      "logo.png",
      "next-env.d.ts",
      "package-lock.json",
      "package.json",
      "project-tree.txt",
      "project_tree.txt",
      "tsconfig.json"
    ],
    "folders": {
      "app": {
        "files": [
          "globals.css",
          "layout.tsx",
          "page.tsx"
        ],
        "folders": {
          "assets": {
            "files": [],
            "folders": {
              "css": {
                "files": [
                  "style.css"
                ],
                "folders": {}
              },
              "fonts": {
                "files": [],
                "folders": {}
              },
              "icons": {
                "files": [],
                "folders": {}
              },
              "images": {
                "files": [],
                "folders": {
                  "categories": {
                    "files": [
                      "bee-products.jpg",
                      "honey.jpg",
                      "natural-oils.jpg",
                      "premium-spices.jpg"
                    ],
                    "folders": {
                      "large": {
                        "files": [
                          "bee-products.jpg",
                          "honey.jpg",
                          "natural-oils.jpg",
                          "primum-spices.jpg"
                        ],
                        "folders": {}
                      }
                    }
                  },
                  "certifications": {
                    "files": [],
                    "folders": {}
                  },
                  "countries": {
                    "files": [],
                    "folders": {}
                  },
                  "gallery": {
                    "files": [],
                    "folders": {}
                  },
                  "hero": {
                    "files": [],
                    "folders": {}
                  },
                  "products": {
                    "files": [],
                    "folders": {
                      "bee-pollen": {
                        "files": [
                          "bee-pollen.jpg"
                        ],
                        "folders": {}
                      },
                      "black-seed-oil": {
                        "files": [
                          "black-seed-oil.jpg"
                        ],
                        "folders": {}
                      },
                      "citrus-honey": {
                        "files": [
                          "citrus-honey.jpg"
                        ],
                        "folders": {}
                      },
                      "clove-honey": {
                        "files": [
                          "clover-honey.jpg"
                        ],
                        "folders": {}
                      },
                      "cumin-powder": {
                        "files": [
                          "cumin-powder.jpg"
                        ],
                        "folders": {}
                      },
                      "garlic-powder": {
                        "files": [
                          "garlic-powder.jpg"
                        ],
                        "folders": {}
                      },
                      "hibiscus-flower": {
                        "files": [
                          "hibiscus-flowers.jpg"
                        ],
                        "folders": {}
                      },
                      "onion-powder": {
                        "files": [
                          "union-powder.jpg"
                        ],
                        "folders": {}
                      },
                      "propolis": {
                        "files": [
                          "propolis.jpg"
                        ],
                        "folders": {}
                      },
                      "pure-beeswax": {
                        "files": [
                          "pure-beeswax.jpg"
                        ],
                        "folders": {}
                      },
                      "royal-jelly": {
                        "files": [
                          "Royal-jelly.jpg"
                        ],
                        "folders": {}
                      },
                      "seven-spices-blend": {
                        "files": [
                          "seven-spices-blend.jpg"
                        ],
                        "folders": {}
                      },
                      "sweet-paprika": {
                        "files": [
                          "sweet-paprika.jpg"
                        ],
                        "folders": {}
                      },
                      "turmeric-powder": {
                        "files": [
                          "turmeric-powder.jpg"
                        ],
                        "folders": {}
                      },
                      "wildflower-honey": {
                        "files": [
                          "wildflower-honey.jpg"
                        ],
                        "folders": {}
                      }
                    }
                  }
                }
              },
              "logos": {
                "files": [
                  "logo.jpg"
                ],
                "folders": {}
              },
              "products": {
                "files": [],
                "folders": {}
              },
              "videos": {
                "files": [],
                "folders": {}
              }
            }
          },
          "js": {
            "files": [
              "script.js"
            ],
            "folders": {
              "core": {
                "files": [
                  "api.js",
                  "config.js",
                  "router.js"
                ],
                "folders": {}
              },
              "modules": {
                "files": [
                  "categories.js",
                  "footer.js",
                  "header.js",
                  "products.js"
                ],
                "folders": {}
              },
              "ui": {
                "files": [
                  "loader.js",
                  "modal.js",
                  "toast.js"
                ],
                "folders": {}
              }
            }
          },
          "views": {
            "files": [
              "about.html",
              "contact.html",
              "home.html",
              "packaging.html",
              "product.html",
              "products.html"
            ],
            "folders": {}
          }
        }
      },
      "backup": {
        "files": [],
        "folders": {
          "2026-07-17_18-51-09": {
            "files": [
              "01_global.json",
              "02_collections.json",
              "03_packaging_system.json",
              "04_packaging_profiles.json",
              "05_master_products.json",
              "06_markets.json",
              "07_documents.json",
              "08_media.json"
            ],
            "folders": {
              "legacy": {
                "files": [
                  "brand.json",
                  "categories.json",
                  "category-extensions.json",
                  "certificates.json",
                  "countries.json",
                  "incoterms.json",
                  "legal-entities.json",
                  "markets.json",
                  "packaging.json",
                  "product-variants.json",
                  "product.schema.json",
                  "products.json",
                  "units.json"
                ],
                "folders": {}
              }
            }
          },
          "2026-07-18_13-18-28": {
            "files": [
              "01_global.json",
              "02_collections.json",
              "03_packaging_system.json",
              "04_packaging_profiles.json",
              "05_master_products.json",
              "06_markets.json",
              "07_documents.json",
              "08_media.json"
            ],
            "folders": {
              "legacy": {
                "files": [
                  "brand.json",
                  "categories.json",
                  "category-extensions.json",
                  "certificates.json",
                  "countries.json",
                  "incoterms.json",
                  "legal-entities.json",
                  "markets.json",
                  "packaging.json",
                  "product-variants.json",
                  "product.schema.json",
                  "products.json",
                  "units.json"
                ],
                "folders": {}
              }
            }
          },
          "2026-07-18_13-21-54": {
            "files": [
              "01_global.json",
              "02_collections.json",
              "03_packaging_system.json",
              "04_packaging_profiles.json",
              "05_master_products.json",
              "06_markets.json",
              "07_documents.json",
              "08_media.json"
            ],
            "folders": {
              "legacy": {
                "files": [
                  "brand.json",
                  "categories.json",
                  "category-extensions.json",
                  "certificates.json",
                  "countries.json",
                  "incoterms.json",
                  "legal-entities.json",
                  "markets.json",
                  "packaging.json",
                  "product-variants.json",
                  "product.schema.json",
                  "products.json",
                  "units.json"
                ],
                "folders": {}
              }
            }
          },
          "2026-07-18_13-49-51": {
            "files": [
              "01_global.json",
              "02_collections.json",
              "03_packaging_system.json",
              "04_packaging_profiles.json",
              "05_master_products.json",
              "06_markets.json",
              "07_documents.json",
              "08_media.json"
            ],
            "folders": {
              "legacy": {
                "files": [
                  "brand.json",
                  "categories.json",
                  "category-extensions.json",
                  "certificates.json",
                  "countries.json",
                  "incoterms.json",
                  "legal-entities.json",
                  "markets.json",
                  "packaging.json",
                  "product-variants.json",
                  "product.schema.json",
                  "products.json",
                  "units.json"
                ],
                "folders": {}
              }
            }
          }
        }
      },
      "cards": {
        "files": [],
        "folders": {}
      },
      "components": {
        "files": [],
        "folders": {}
      },
      "data": {
        "files": [
          "01_global.json",
          "02_collections.json",
          "03_packaging_system.json",
          "04_packaging_profiles.json",
          "05_master_products.json",
          "06_markets.json",
          "07_documents.json",
          "08_media.json"
        ],
        "folders": {
          "legacy": {
            "files": [
              "brand.json",
              "categories.json",
              "category-extensions.json",
              "certificates.json",
              "countries.json",
              "incoterms.json",
              "legal-entities.json",
              "markets.json",
              "packaging.json",
              "product-variants.json",
              "product.schema.json",
              "products.json",
              "units.json"
            ],
            "folders": {}
          }
        }
      },
      "docs": {
        "files": [
          "README.md"
        ],
        "folders": {
          "architecture": {
            "files": [
              "SYSTEM_ARCHITECTURE.md"
            ],
            "folders": {}
          },
          "packaging": {
            "files": [
              "packaging_master.md",
              "PACKING_CODES.md"
            ],
            "folders": {}
          },
          "products": {
            "files": [
              "PRODUCT_CODE.md",
              "PRODUCT_DATABASE.md",
              "PRODUCT_LIBRARY.md",
              "PRODUCT_MASTER.md",
              "PRODUCT_TEMPLATE.md"
            ],
            "folders": {}
          },
          "standards": {
            "files": [
              "01_BRAND_STANDARD.md"
            ],
            "folders": {}
          }
        }
      },
      "forms": {
        "files": [],
        "folders": {}
      },
      "lib": {
        "files": [],
        "folders": {
          "data": {
            "files": [
              "collections.ts",
              "documents.ts",
              "global.ts",
              "markets.ts",
              "media.ts",
              "packaging-profiles.ts",
              "packaging.ts",
              "products.ts"
            ],
            "folders": {
              "validators": {
                "files": [],
                "folders": {}
              }
            }
          },
          "helpers": {
            "files": [],
            "folders": {}
          }
        }
      },
      "packaging": {
        "files": [],
        "folders": {}
      },
      "public": {
        "files": [],
        "folders": {
          "backgrounds": {
            "files": [],
            "folders": {}
          },
          "brand": {
            "files": [],
            "folders": {}
          },
          "certifications": {
            "files": [],
            "folders": {}
          },
          "flags": {
            "files": [],
            "folders": {}
          },
          "icons": {
            "files": [],
            "folders": {}
          },
          "mokups": {
            "files": [],
            "folders": {}
          },
          "packaging": {
            "files": [],
            "folders": {}
          },
          "products": {
            "files": [],
            "folders": {}
          }
        }
      },
      "reports": {
        "files": [
          "migration-report.json"
        ],
        "folders": {}
      },
      "schema": {
        "files": [
          "entity.schema.json"
        ],
        "folders": {}
      },
      "scripts": {
        "files": [
          "audit-project.js",
          "backup-data.js",
          "migrate-schema.js",
          "validate-schema.js"
        ],
        "folders": {}
      },
      "ui": {
        "files": [],
        "folders": {}
      }
    }
  }
}